{"_default": {"80": {"username": "EMMM", "score": 79079, "timestamp": "2018-09-09 19:02:10.542013"}, "81": {"username": "ESPRESSO", "score": 77452, "timestamp": "2018-09-09 19:55:19.782009"}, "82": {"username": "ROY", "score": 85366, "timestamp": "2018-09-09 20:22:49.270067"}, "83": {"username": "4s", "score": 84222, "timestamp": "2018-09-09 20:55:38.771678"}, "84": {"username": "", "score": 78748, "timestamp": "2018-09-09 22:13:30.492054"}, "85": {"username": "RED", "score": 77753, "timestamp": "2018-09-09 22:46:35.723262"}, "86": {"username": "THIS IS A NEW SCORE", "score": 77447, "timestamp": "2018-09-09 23:22:13.359722"}, "87": {"username": "123", "score": 75639, "timestamp": "2018-09-09 23:27:01.855177"}, "88": {"username": "2", "score": 18029, "timestamp": "2018-09-09 23:27:11.672702"}, "89": {"username": "", "score": 75788, "timestamp": "2018-09-09 23:27:30.298618"}, "90": {"username": "", "score": 37831, "timestamp": "2018-09-09 23:27:45.956740"}, "91": {"username": "", "score": 0, "timestamp": "2018-09-09 23:27:48.803331"}, "92": {"username": "", "score": 0, "timestamp": "2018-09-09 23:27:50.395938"}, "93": {"username": "", "score": 0, "timestamp": "2018-09-09 23:27:51.340775"}, "94": {"username": "", "score": 0, "timestamp": "2018-09-09 23:27:52.337990"}, "95": {"username": "", "score": 0, "timestamp": "2018-09-09 23:27:53.402380"}, "96": {"username": "", "score": 0, "timestamp": "2018-09-09 23:27:54.330157"}, "97": {"username": "", "score": 0, "timestamp": "2018-09-09 23:27:55.323024"}, "98": {"username": "", "score": 0, "timestamp": "2018-09-09 23:27:56.345139"}, "99": {"username": "", "score": 0, "timestamp": "2018-09-09 23:27:57.335366"}, "100": {"username": "", "score": 0, "timestamp": "2018-09-09 23:27:58.335888"}, "101": {"username": "", "score": 0, "timestamp": "2018-09-09 23:27:59.348822"}, "102": {"username": "", "score": 0, "timestamp": "2018-09-09 23:28:00.344788"}, "103": {"username": "", "score": 0, "timestamp": "2018-09-09 23:28:01.342862"}, "104": {"username": "", "score": 0, "timestamp": "2018-09-09 23:28:02.357847"}, "105": {"username": "", "score": 0, "timestamp": "2018-09-09 23:33:51.148483"}, "106": {"username": "1231231231231231231", "score": 17735, "timestamp": "2018-09-10 09:43:18.128408"}, "107": {"username": "213123123312312312", "score": 9086, "timestamp": "2018-09-10 09:53:09.754458"}, "108": {"username": "<<<<~~~~", "score": 8617, "timestamp": "2018-09-10 11:29:47.788200"}, "109": {"username": "3", "score": 8341, "timestamp": "2018-09-10 13:33:18.103052"}, "110": {"username": "q", "score": 15608, "timestamp": "2018-09-10 13:42:49.148811"}, "111": {"username": "123", "score": 8895, "timestamp": "2018-09-10 15:33:16.414774"}, "112": {"username": "234", "score": 8835, "timestamp": "2018-09-10 15:35:52.171122"}, "113": {"username": "123", "score": 8832, "timestamp": "2018-09-10 15:36:41.558332"}, "114": {"username": "234", "score": 8205, "timestamp": "2018-09-10 15:43:41.985316"}, "115": {"username": "here", "score": 17344, "timestamp": "2018-09-10 15:44:36.055454"}, "116": {"username": "Here is my name", "score": 8668, "timestamp": "2018-09-10 15:44:50.400689"}, "117": {"username": "1022222", "score": 8157, "timestamp": "2018-09-10 15:50:44.692583"}, "118": {"username": "10222222", "score": 43380, "timestamp": "2018-09-10 15:50:59.709294"}, "119": {"username": "213", "score": 8580, "timestamp": "2018-09-10 16:08:46.622856"}, "120": {"username": "434324", "score": 8799, "timestamp": "2018-09-10 16:17:29.188933"}, "121": {"username": "434324", "score": 8937, "timestamp": "2018-09-10 16:17:39.639520"}, "122": {"username": "123", "score": 8749, "timestamp": "2018-09-10 16:53:06.764989"}, "123": {"username": "12312321", "score": 8828, "timestamp": "2018-09-10 16:53:20.777932"}, "124": {"username": "1", "score": 17305, "timestamp": "2018-09-10 16:56:45.672013"}, "125": {"username": "12", "score": 8792, "timestamp": "2018-09-10 16:58:29.312826"}, "126": {"username": "12", "score": 8676, "timestamp": "2018-09-10 17:15:50.620803"}, "127": {"username": "123", "score": 17810, "timestamp": "2018-09-10 17:18:58.561581"}, "128": {"username": "1221321", "score": 8632, "timestamp": "2018-09-10 18:30:54.798270"}, "129": {"username": "12", "score": 8868, "timestamp": "2018-09-10 18:32:09.046983"}, "130": {"username": "123", "score": 8529, "timestamp": "2018-09-10 18:33:17.243515"}, "131": {"username": "3124", "score": 14656, "timestamp": "2018-09-10 18:36:54.948681"}, "132": {"username": "32432", "score": 8633, "timestamp": "2018-09-10 18:39:32.304436"}, "133": {"username": "234", "score": 8946, "timestamp": "2018-09-10 18:42:40.944691"}, "134": {"username": "ewrewrew", "score": 8508, "timestamp": "2018-09-10 18:43:10.179435"}, "135": {"username": "324", "score": 8885, "timestamp": "2018-09-10 18:43:38.894399"}, "136": {"username": "23423", "score": 8554, "timestamp": "2018-09-10 18:46:03.172479"}, "137": {"username": "23324", "score": 8327, "timestamp": "2018-09-10 18:53:18.455087"}, "138": {"username": "2332", "score": 16539, "timestamp": "2018-09-10 18:53:27.037915"}, "139": {"username": "123", "score": 8651, "timestamp": "2018-09-10 18:54:34.452490"}, "140": {"username": "r2rewc", "score": 8432, "timestamp": "2018-09-10 18:57:25.192039"}, "141": {"username": "sada", "score": 13581, "timestamp": "2018-09-10 18:58:44.725368"}, "142": {"username": "sad3ewgvd", "score": 8788, "timestamp": "2018-09-10 19:00:00.098173"}, "143": {"username": "asdas", "score": 8337, "timestamp": "2018-09-10 19:00:49.288480"}, "144": {"username": "sad", "score": 8157, "timestamp": "2018-09-10 19:02:37.142072"}, "145": {"username": "as", "score": 8482, "timestamp": "2018-09-10 19:03:10.387102"}, "146": {"username": "asd", "score": 8686, "timestamp": "2018-09-10 19:03:51.082635"}, "147": {"username": "sdfsdfew", "score": 8021, "timestamp": "2018-09-10 19:05:09.959507"}, "148": {"username": "erwfvcd", "score": 8903, "timestamp": "2018-09-10 19:06:21.346782"}, "149": {"username": "WORKING?", "score": 17258, "timestamp": "2018-09-10 19:08:04.271351"}, "150": {"username": "nfdlkslt43", "score": 8301, "timestamp": "2018-09-10 19:08:50.312413"}, "151": {"username": "asdsad32", "score": 17429, "timestamp": "2018-09-10 19:11:56.492023"}, "152": {"username": "asdsad32", "score": 17862, "timestamp": "2018-09-10 19:12:05.225716"}, "153": {"username": "wqefdsad", "score": 8706, "timestamp": "2018-09-10 19:12:30.549694"}, "154": {"username": "wqefdsaddsfdsf", "score": 17327, "timestamp": "2018-09-10 19:12:40.828739"}, "155": {"username": "wqefdsaddsfdsf", "score": 42257, "timestamp": "2018-09-10 19:12:54.756661"}, "156": {"username": "wqefdsaddsfdsfs", "score": 8597, "timestamp": "2018-09-10 19:13:10.684110"}}}